{
  "port": 9223,
  "title": "4S店免费膜能贴吗？",
  "body": "惠州的车友们，今天聊一个几乎所有新车车主都会纠结的问题——4S店送的那个免费太阳膜，到底能不能贴？\n\n先给结论：能贴，但我劝你想清楚再贴。\n\n我自己干贴膜20年了，见过太多车主为了省这笔钱，结果花大价钱去撕膜重贴的案例。\n\n为什么4S店送的膜不推荐？\n\n不是说4S店不好，而是送的膜成本摆在那。大部分是基础染色膜，隔热效果有限，用个一两年就起泡、褪色，严重的还会留胶，后期撕膜又是一笔费用。\n\n那应该怎么办？\n\n如果你对隔热有要求（广东这天气懂的），建议提车时跟4S店谈：\n1. 把送的膜折成其他赠品（脚垫、保养券都行）\n2. 加点预算升级正规品牌膜（比如龙膜这种有官方质保的）\n\n惠州想贴膜的朋友，评论区留车型，我免费给你出方案。不一定要来我店里，但至少让你心里有个底，去别家也不怕被忽悠。\n\n#惠州汽车贴膜 #龙膜 #新车必备 #贴膜避坑 #惠州同城 #尊车港",
  "card_title": "4S店免费膜能贴吗？",
  "card_subtitle": "20年贴膜老炮告诉你真相\\n惠州惠城区·尊车港龙膜",
  "card_tags": ["惠州贴膜", "龙膜正品", "避坑指南", "惠州同城"],
  "card_style": "dark",
  "images": []
}
